[{"STAFF NO.":"CON030","NAME":"ELIJAH O DEDE","GRADE":"KBC 1","DESIGNATION":"CHIEF EXECUTIVE OFFICER"},{"STAFF NO.":"CON060","NAME":"JAMES OREYO ODERO","GRADE":"KBC 4","DESIGNATION":"MANAGER 3"},{"STAFF NO.":"KBC140","NAME":"VINCENT OMONDI OKIRO","GRADE":"KBC 8","DESIGNATION":"CLERK"},{"STAFF NO.":"CON081","NAME":"GRACE WANGUI NDUTA","GRADE":"CONTRACT","DESIGNATION":"CONTRACT"},{"STAFF NO.":"CON082","NAME":"YVETTE ROSA MWIMA","GRADE":"CONTRACT","DESIGNATION":"CONTRACT"},{"STAFF NO.":"KBC163","NAME":"DENNIS WAFULA WANYONYI","GRADE":"KBC 8","DESIGNATION":"CLERK"},{"STAFF NO.":"KBC108","NAME":"CATHERINE ACHIENG ODERO","GRADE":"KBC 7","DESIGNATION":"SUPERVISER"},{"STAFF NO.":"KBC161","NAME":"MARTHA WAMWITHA NJAGI","GRADE":"KBC 8","DESIGNATION":"CLERK"},{"STAFF NO.":"KBC133","NAME":"PETER OTIENO KAYE","GRADE":"KBC 8","DESIGNATION":"CLERK"},{"STAFF NO.":"KBC134","NAME":"GEDION MWANGI MWEHA","GRADE":"KBC 8","DESIGNATION":"CLERK"},{"STAFF NO.":"CON071","NAME":"CAROLINE WANGECHI MUCHIRAH","GRADE":"KBC 8","DESIGNATION":"CLERK"},{"STAFF NO.":"CON077","NAME":"CALVIN PAUL KWAME ORUYA","GRADE":"CONTRACT","DESIGNATION":"CONTRACT"},{"STAFF NO.":"CON078","NAME":"JOSEPH WAINANINA MUNGAI","GRADE":"CONTRACT","DESIGNATION":"CONTRACT"},{"STAFF NO.":"CON079","NAME":"FAITH NALIAKA MUNIAFU","GRADE":"CONTRACT","DESIGNATION":"CONTRACT"},{"STAFF NO.":"CON084","NAME":"STANLEY KIPKORIR KIBET","GRADE":"CONTRACT","DESIGNATION":"CONTRACT"},{"STAFF NO.":"CON087","NAME":"CLARE JANET AMONDI OGINAH","GRADE":"CONTRACT","DESIGNATION":"CONTRACT"},{"STAFF NO.":"CON088","NAME":"KASUNGWA NZOMO","GRADE":"CONTRACT","DESIGNATION":"CONTRACT"},{"STAFF NO.":"CON090","NAME":"LILIAN WANGUI GITAU","GRADE":"CONTRACT","DESIGNATION":"CONTRACT"},{"STAFF NO.":"KBC069","NAME":"MARGARET KABERA","GRADE":"KBC 6","DESIGNATION":"OFFICER 2"},{"STAFF NO.":"KBC100","NAME":"WALTER OWUOR OGUTU","GRADE":"KBC 5","DESIGNATION":"OFFICER 1"},{"STAFF NO.":"KBC101","NAME":"GURACHA GALGALO GALGALO","GRADE":"KBC 8","DESIGNATION":"CLERK"},{"STAFF NO.":"KBC102","NAME":"CHRISTINE MAKOMBO NDELEKO","GRADE":"KBC 7","DESIGNATION":"SUPERVISER"},{"STAFF NO.":"KBC104","NAME":"DORCAS AKINYI ODHIAMBO","GRADE":"KBC 7","DESIGNATION":"SUPERVISER"},{"STAFF NO.":"KBC106","NAME":"SELLAH BENTER OTIENO","GRADE":"KBC 7","DESIGNATION":"SUPERVISER"},{"STAFF NO.":"KBC141","NAME":"JOSEPH MWANZIA VEKYA","GRADE":"KBC 8","DESIGNATION":"CLERK"},{"STAFF NO.":"KBC144","NAME":"HENRY MUGIIRA KAARIA","GRADE":"KBC 6","DESIGNATION":"OFFICER 2"},{"STAFF NO.":"KBC151","NAME":"JAMES MUTUA MUTISYA","GRADE":"KBC 8","DESIGNATION":"CLERK"},{"STAFF NO.":"CON085","NAME":"JAMILLA UCHI KUTA","GRADE":"CONTRACT","DESIGNATION":"CONTRACT"},{"STAFF NO.":"CON086","NAME":"KEREN MAKENA MAGANA","GRADE":"KBC 8","DESIGNATION":"CLERK"},{"STAFF NO.":"CON091","NAME":"MARION ABUKO NJONI","GRADE":"CONTRACT","DESIGNATION":"CONTRACT"},{"STAFF NO.":"CON092","NAME":"SHARON SILAU  PARTOIP","GRADE":"CONTRACT","DESIGNATION":"CONTRACT"},{"STAFF NO.":"CON093","NAME":"SAMIR WANGATIA MAKOKHA","GRADE":"CONTRACT","DESIGNATION":"CONTRACT"},{"STAFF NO.":"CON094","NAME":"BRITER AWUOR OUMA","GRADE":"CONTRACT","DESIGNATION":"CONTRACT"},{"STAFF NO.":"KBC056","NAME":"JANE WANJIRU","GRADE":"KBC 6","DESIGNATION":"OFFICER 2"},{"STAFF NO.":"KBC105","NAME":"ARTHUR OGUTU","GRADE":"KBC 6","DESIGNATION":"OFFICER 2"},{"STAFF NO.":"KBC114","NAME":"NICHOLAS MACHORA MOSOCHO","GRADE":"KBC 7","DESIGNATION":"SUPERVISER"},{"STAFF NO.":"KBC137","NAME":"ZEINAB IBRAHIM ABDILLE","GRADE":"KBC 8","DESIGNATION":"CLERK"},{"STAFF NO.":"KBC142","NAME":"FANCY JERUTO NGETICH","GRADE":"KBC 8","DESIGNATION":"CLERK"},{"STAFF NO.":"KBC143","NAME":"CAROLINE GATWIRI GITONGA","GRADE":"KBC 8","DESIGNATION":"CLERK"},{"STAFF NO.":"KBC165","NAME":"SERAH NJERI MAKUMI","GRADE":"KBC 8","DESIGNATION":"CLERK"},{"STAFF NO.":"CON080","NAME":"JOYCE CHERONO SONGOL","GRADE":"CONTRACT","DESIGNATION":"CONTRACT"},{"STAFF NO.":"CON083","NAME":"KENNEDY OKUMU MUKALAMA","GRADE":"CONTRACT","DESIGNATION":"CONTRACT"},{"STAFF NO.":"KBC138","NAME":"NELSON NDUVA MUASYA","GRADE":"KBC 6","DESIGNATION":"OFFICER 2"},{"STAFF NO.":"KBC149","NAME":"ANTONY WAMBIRI NJERI","GRADE":"KBC 7","DESIGNATION":"SUPERVISER"},{"STAFF NO.":"KBC154","NAME":"YVONNE MUHONJA OBENI","GRADE":"KBC 8","DESIGNATION":"CLERK"},{"STAFF NO.":"KBC049","NAME":"LUCY MBOGORI","GRADE":"KBC 7","DESIGNATION":"SUPERVISER"},{"STAFF NO.":"KBC107","NAME":"DANIEL MARIGA NJOROGE","GRADE":"KBC 6","DESIGNATION":"OFFICER 2"},{"STAFF NO.":"KBC146","NAME":"KEVIN MAKOKHA WEBUYE","GRADE":"KBC 8","DESIGNATION":"CLERK"},{"STAFF NO.":"KBC153","NAME":"EMMANUEL WANGA ITINDI","GRADE":"KBC 8","DESIGNATION":"CLERK"},{"STAFF NO.":"KBC155","NAME":"WALTER ONYANGO ODHIAMBO","GRADE":"KBC 8","DESIGNATION":"CLERK"},{"STAFF NO.":"CON005","NAME":"JOSEPH JAMES OKANA","GRADE":"KBC 2","DESIGNATION":"ASST. GENERAL MANAGER"},{"STAFF NO.":"CON023","NAME":"EVERLYNE K ONYANGO","GRADE":"KBC 10","DESIGNATION":"TEA GIRL"},{"STAFF NO.":"CON042","NAME":"JOHN KIPRUTTO KIPTOO","GRADE":"KBC 10","DESIGNATION":"MESSENGER"},{"STAFF NO.":"CON055","NAME":"ANNE WAITHIRA MWANGI","GRADE":"KBC 6","DESIGNATION":"OFFICER 2"},{"STAFF NO.":"CON059","NAME":"FREDRICK WANJALA MAKHONGE","GRADE":"KBC 4","DESIGNATION":"MANAGER 3"},{"STAFF NO.":"CON067","NAME":"NELSON LEWA MAILU","GRADE":"KBC 9","DESIGNATION":"DRIVER"},{"STAFF NO.":"CON076","NAME":"MAUREEN ACHIENG OJWANG","GRADE":"KBC 10","DESIGNATION":"MESSENGER"},{"STAFF NO.":"KBC064","NAME":"JOEL MUGAH","GRADE":"KBC 8","DESIGNATION":"CLERK"},{"STAFF NO.":"KBC109","NAME":"PETER MALELA OSURI","GRADE":"KBC 7","DESIGNATION":"SUPERVISER"},{"STAFF NO.":"KBC122","NAME":"WILSON DOMOLIMA YOPONGOLE","GRADE":"KBC 10","DESIGNATION":"MESSENGER"},{"STAFF NO.":"KBC128","NAME":"MICHAEL LCHARPANA LETOLE","GRADE":"KBC 10","DESIGNATION":"MESSENGER"},{"STAFF NO.":"KBC135","NAME":"CINDERELLAH SARAH MAKOKHA","GRADE":"KBC 7","DESIGNATION":"SUPERVISER"},{"STAFF NO.":"KBC145","NAME":"FRANCIS KANYAGO KARIUKI","GRADE":"KBC 7","DESIGNATION":"SUPERVISER"},{"STAFF NO.":"KBC167","NAME":"CHRISTOPHER MUTINDA MUUNDA","GRADE":"KBC 9","DESIGNATION":"DRIVER"},{"STAFF NO.":"CON036","NAME":"DILLIAS INSI MWAKESI MWADIME","GRADE":"KBC 6","DESIGNATION":"OFFICER 2"},{"STAFF NO.":"CON065","NAME":"STEVE ISINGA BIKO","GRADE":"KBC 3","DESIGNATION":"MANAGER 2"},{"STAFF NO.":"KBC164","NAME":"KALVIN SAITOTI SIMIYU","GRADE":"KBC 6","DESIGNATION":"OFFICER 2"},{"STAFF NO.":"KBC123","NAME":"JOSHUA KYALO KAUNDA","GRADE":"KBC 6","DESIGNATION":"OFFICER 2"},{"STAFF NO.":"KBC125","NAME":"JOSEPH KYALO KITOO","GRADE":"KBC 7","DESIGNATION":"SUPERVISER"},{"STAFF NO.":"CON057","NAME":"MAURICE KIBET MUTWOL","GRADE":"KBC 2","DESIGNATION":"ASST. GENERAL MANAGER"},{"STAFF NO.":"CON064","NAME":"DORIS MUENI MUTIE","GRADE":"KBC 8","DESIGNATION":"CLERK"},{"STAFF NO.":"CON068","NAME":"PATRICIAH NASIKAWA MBAYAKI","GRADE":"KBC 8","DESIGNATION":"CLERK"},{"STAFF NO.":"CON069","NAME":"WINNIE AWOUR KASOLY","GRADE":"KBC 8","DESIGNATION":"CLERK"},{"STAFF NO.":"CON070","NAME":"AILI CHEPKWEMOI","GRADE":"KBC 8","DESIGNATION":"CLERK"},{"STAFF NO.":"KBC063","NAME":"EDWARD O MATOKE","GRADE":"KBC 7","DESIGNATION":"SUPERVISER"},{"STAFF NO.":"KBC066","NAME":"SUSAN WANDERE","GRADE":"KBC 10","DESIGNATION":"MESSENGER"},{"STAFF NO.":"KBC082","NAME":"ERIC KIPTUM TEIMUGE","GRADE":"KBC 7","DESIGNATION":"SUPERVISER"},{"STAFF NO.":"KBC127","NAME":"MICHAEL EMURUDU IPERO","GRADE":"KBC 8","DESIGNATION":"CLERK"},{"STAFF NO.":"KBC136","NAME":"JACKSON LORIONO PKAROY","GRADE":"KBC 8","DESIGNATION":"CLERK"},{"STAFF NO.":"KBC152","NAME":"POLYCARP MUNANGA NYONJE","GRADE":"KBC 8","DESIGNATION":"CLERK"},{"STAFF NO.":"KBC160","NAME":"DENIS OCHIENG NYONGO","GRADE":"KBC 8","DESIGNATION":"CLERK"},{"STAFF NO.":"KBC166","NAME":"RACHEL SHALI WAMWANDU","GRADE":"KBC 8","DESIGNATION":"CLERK"},{"STAFF NO.":"CON024","NAME":"JACKLYNE ADEMA","GRADE":"CLEANER","DESIGNATION":"CLEANER"},{"STAFF NO.":"CON032","NAME":"MARCELA SHIGHADI GOMBE","GRADE":"KBC 6","DESIGNATION":"OFFICER 2"},{"STAFF NO.":"CON043","NAME":"JENNIFFER NDUNGE KIMANTHI","GRADE":"CLEANER","DESIGNATION":"CLEANER"},{"STAFF NO.":"CON045","NAME":"JANE WAMBUI JUMA","GRADE":"CLEANER","DESIGNATION":"CLEANER"},{"STAFF NO.":"CON047","NAME":"PATRICK MWAKI KADENGE","GRADE":"CLEANER","DESIGNATION":"CLEANER"},{"STAFF NO.":"CON050","NAME":"JOSEPH M MURAMBI","GRADE":"KBC 4","DESIGNATION":"MANAGER 3"},{"STAFF NO.":"CON053","NAME":"EVANS AMBARE KASIGANE","GRADE":"CLEANER","DESIGNATION":"CLEANER"},{"STAFF NO.":"CON054","NAME":"JAMES JOGINDER ESIBWE","GRADE":"CLEANER","DESIGNATION":"CLEANER"},{"STAFF NO.":"CON056","NAME":"GERALD GATHURU CHEGE","GRADE":"CLEANER","DESIGNATION":"CLEANER"},{"STAFF NO.":"CON066","NAME":"PAUL OKOTH NYADUDI","GRADE":"CLEANER","DESIGNATION":"CLEANER"},{"STAFF NO.":"KBC092","NAME":"ISABELLA FARRAR","GRADE":"KBC 8","DESIGNATION":"CLERK"},{"STAFF NO.":"KBC126","NAME":"GODFREY OSOGO MACHIO","GRADE":"KBC 8","DESIGNATION":"CLERK"},{"STAFF NO.":"KBC131","NAME":"RHODA KAVUTHA MUNYOKI","GRADE":"KBC 6","DESIGNATION":"OFFICER 2"},{"STAFF NO.":"KBC132","NAME":"SUSAN WAMBUI KARU","GRADE":"KBC 7","DESIGNATION":"SUPERVISER"},{"STAFF NO.":"KBC157","NAME":"EUCELYN ANDANJE NANDWA","GRADE":"KBC8","DESIGNATION":"CLERK"}]